qubisafe/__init__.py
qubisafe/website.py
qubisafe-0.1.0.dist-info/LICENSE
qubisafe-0.1.0.dist-info/METADATA
qubisafe-0.1.0.dist-info/WHEEL
qubisafe-0.1.0.dist-info/top_level.txt
qubisafe-0.1.0.dist-info/RECORD
